{"_id":"mixpanel","_rev":"63-96f64685cee4c931a787d85eab8aae4b","name":"mixpanel","description":"A simple server-side API for mixpanel","dist-tags":{"latest":"0.5.0"},"versions":{"0.0.2":{"name":"mixpanel","description":"A simple API for mixpanel","keywords":["mixpanel","analytics","api","stats"],"version":"0.0.2","homepage":"https://github.com/carlsverre/mixpanel-node","author":{"name":"Carl Sverre","url":"http://carlsverre.com"},"main":"lib/mixpanel-node","directories":{"lib":"lib"},"repository":{"type":"git","url":"http://github.com/carlsverre/mixpanel-node.git"},"engines":{"node":">=0.3.8"},"_id":"mixpanel@0.0.2","_nodeSupported":true,"_npmVersion":"0.2.12-1","_nodeVersion":"v0.4.0-pre","dist":{"shasum":"e29fdaa8beaca17c54c167317b92dc1dcec24a23","tarball":"https://registry.npmjs.org/mixpanel/-/mixpanel-0.0.2.tgz"}},"0.0.3":{"name":"mixpanel","description":"A simple API for mixpanel","keywords":["mixpanel","analytics","api","stats"],"version":"0.0.3","homepage":"https://github.com/carlsverre/mixpanel-node","author":{"name":"Carl Sverre","url":"http://carlsverre.com"},"main":"lib/mixpanel-node","directories":{"lib":"lib"},"repository":{"type":"git","url":"http://github.com/carlsverre/mixpanel-node.git"},"engines":{"node":">=0.4.0"},"_id":"mixpanel@0.0.3","_engineSupported":true,"_npmVersion":"0.2.18","_nodeVersion":"v0.4.0","files":[""],"_defaultsLoaded":true,"dist":{"shasum":"8c674f063037cd9a506337a1419c8b78388dbb94","tarball":"https://registry.npmjs.org/mixpanel/-/mixpanel-0.0.3.tgz"}},"0.0.4":{"name":"mixpanel","description":"A simple API for mixpanel","keywords":["mixpanel","analytics","api","stats"],"version":"0.0.4","homepage":"https://github.com/carlsverre/mixpanel-node","author":{"name":"Carl Sverre","url":"http://carlsverre.com"},"main":"lib/mixpanel-node","directories":{"lib":"lib"},"repository":{"type":"git","url":"git://github.com/carlsverre/mixpanel-node.git"},"engines":{"node":">=0.4.0"},"_id":"mixpanel@0.0.4","_engineSupported":true,"_npmVersion":"0.3.4","_nodeVersion":"v0.4.8","files":[""],"_defaultsLoaded":true,"dist":{"shasum":"b7445aab9449e0bfb08ac20c26cffaa703048667","tarball":"https://registry.npmjs.org/mixpanel/-/mixpanel-0.0.4.tgz"}},"0.0.5":{"name":"mixpanel","description":"A simple API for mixpanel","keywords":["mixpanel","analytics","api","stats"],"version":"0.0.5","homepage":"https://github.com/carlsverre/mixpanel-node","author":{"name":"Carl Sverre","url":"http://carlsverre.com"},"main":"lib/mixpanel-node","directories":{"lib":"lib"},"repository":{"type":"git","url":"git://github.com/carlsverre/mixpanel-node.git"},"engines":{"node":">=0.4.0"},"_npmJsonOpts":{"file":"/Users/carl/.npm/mixpanel/0.0.5/package/package.json","wscript":false,"contributors":false,"serverjs":false},"_id":"mixpanel@0.0.5","dependencies":{},"devDependencies":{},"_engineSupported":true,"_npmVersion":"1.0.27","_nodeVersion":"v0.4.11","_defaultsLoaded":true,"dist":{"shasum":"b45478e581a88662b3aeb6da341e594acffb5184","tarball":"https://registry.npmjs.org/mixpanel/-/mixpanel-0.0.5.tgz"},"maintainers":[{"name":"carlsverre","email":"mail@carlsverre.com"}]},"0.0.6":{"name":"mixpanel","description":"A simple API for mixpanel","keywords":["mixpanel","analytics","api","stats"],"version":"0.0.6","homepage":"https://github.com/carlsverre/mixpanel-node","author":{"name":"Carl Sverre"},"main":"lib/mixpanel-node","directories":{"lib":"lib"},"repository":{"type":"git","url":"git://github.com/carlsverre/mixpanel-node.git"},"engines":{"node":">=0.4.0"},"_npmUser":{"name":"carlsverre","email":"accounts@carlsverre.com"},"_id":"mixpanel@0.0.6","dependencies":{},"devDependencies":{},"optionalDependencies":{},"_engineSupported":true,"_npmVersion":"1.1.12","_nodeVersion":"v0.6.14","_defaultsLoaded":true,"dist":{"shasum":"c58ec3bbeb50ff86cc2ecd15cfeebfec37e8aa2a","tarball":"https://registry.npmjs.org/mixpanel/-/mixpanel-0.0.6.tgz"},"maintainers":[{"name":"carlsverre","email":"mail@carlsverre.com"}]},"0.0.7":{"name":"mixpanel","description":"A simple API for mixpanel","keywords":["mixpanel","analytics","api","stats"],"version":"0.0.7","homepage":"https://github.com/carlsverre/mixpanel-node","author":{"name":"Carl Sverre"},"main":"lib/mixpanel-node","directories":{"lib":"lib"},"repository":{"type":"git","url":"http://github.com/carlsverre/mixpanel-node.git"},"engines":{"node":">=0.6.0"},"scripts":{"test":"bin/run_tests"},"devDependencies":{"nodeunit":"0.7","sinon":"1.4"},"_id":"mixpanel@0.0.7","dist":{"shasum":"2eaaf1d63232d2d493df899fd6bafd98337ef7c4","tarball":"https://registry.npmjs.org/mixpanel/-/mixpanel-0.0.7.tgz"},"_npmVersion":"1.1.59","_npmUser":{"name":"carlsverre","email":"accounts@carlsverre.com"},"maintainers":[{"name":"carlsverre","email":"mail@carlsverre.com"}]},"0.0.8":{"name":"mixpanel","description":"A simple API for mixpanel","keywords":["mixpanel","analytics","api","stats"],"version":"0.0.8","homepage":"https://github.com/carlsverre/mixpanel-node","author":{"name":"Carl Sverre"},"main":"lib/mixpanel-node","directories":{"lib":"lib"},"repository":{"type":"git","url":"git://github.com/carlsverre/mixpanel-node.git"},"engines":{"node":">=0.6.0"},"scripts":{"test":"bin/run_tests"},"devDependencies":{"nodeunit":"0.7","sinon":"1.4"},"_npmUser":{"name":"carlsverre","email":"accounts@carlsverre.com"},"_id":"mixpanel@0.0.8","dependencies":{},"optionalDependencies":{},"_engineSupported":true,"_npmVersion":"1.1.4","_nodeVersion":"v0.6.12","_defaultsLoaded":true,"dist":{"shasum":"06e98bec69f068975b88cba0e629adb626bd2584","tarball":"https://registry.npmjs.org/mixpanel/-/mixpanel-0.0.8.tgz"},"maintainers":[{"name":"carlsverre","email":"mail@carlsverre.com"}]},"0.0.9":{"name":"mixpanel","description":"A simple API for mixpanel","keywords":["mixpanel","analytics","api","stats"],"version":"0.0.9","homepage":"https://github.com/carlsverre/mixpanel-node","author":{"name":"Carl Sverre"},"main":"lib/mixpanel-node","directories":{"lib":"lib"},"repository":{"type":"git","url":"git://github.com/carlsverre/mixpanel-node.git"},"engines":{"node":">=0.6.0"},"scripts":{"test":"bin/run_tests"},"devDependencies":{"nodeunit":"0.7","sinon":"1.4"},"_npmUser":{"name":"carlsverre","email":"accounts@carlsverre.com"},"_id":"mixpanel@0.0.9","dependencies":{},"optionalDependencies":{},"_engineSupported":true,"_npmVersion":"1.1.4","_nodeVersion":"v0.6.12","_defaultsLoaded":true,"dist":{"shasum":"065f7bc9245af31a906e2a65df91f7a945a1edb3","tarball":"https://registry.npmjs.org/mixpanel/-/mixpanel-0.0.9.tgz"},"maintainers":[{"name":"carlsverre","email":"mail@carlsverre.com"}]},"0.0.10":{"name":"mixpanel","description":"A simple API for mixpanel","keywords":["mixpanel","analytics","api","stats"],"version":"0.0.10","homepage":"https://github.com/carlsverre/mixpanel-node","author":{"name":"Carl Sverre"},"main":"lib/mixpanel-node","directories":{"lib":"lib"},"repository":{"type":"git","url":"git://github.com/carlsverre/mixpanel-node.git"},"engines":{"node":">=0.6.0"},"scripts":{"test":"bin/run_tests"},"devDependencies":{"nodeunit":"0.7","sinon":"1.4"},"_npmUser":{"name":"carlsverre","email":"accounts@carlsverre.com"},"_id":"mixpanel@0.0.10","dependencies":{},"optionalDependencies":{},"_engineSupported":true,"_npmVersion":"1.1.4","_nodeVersion":"v0.6.12","_defaultsLoaded":true,"dist":{"shasum":"f3d90aec799cfdd5292d7afe9437b73c8c4d9c4a","tarball":"https://registry.npmjs.org/mixpanel/-/mixpanel-0.0.10.tgz"},"maintainers":[{"name":"carlsverre","email":"mail@carlsverre.com"}]},"0.0.11":{"name":"mixpanel","description":"A simple API for mixpanel","keywords":["mixpanel","analytics","api","stats"],"version":"0.0.11","homepage":"https://github.com/carlsverre/mixpanel-node","author":{"name":"Carl Sverre"},"main":"lib/mixpanel-node","directories":{"lib":"lib"},"repository":{"type":"git","url":"git://github.com/carlsverre/mixpanel-node.git"},"engines":{"node":">=0.6.0"},"scripts":{"test":"bin/run_tests"},"devDependencies":{"nodeunit":"0.7","sinon":"1.4"},"_npmUser":{"name":"carlsverre","email":"accounts@carlsverre.com"},"_id":"mixpanel@0.0.11","dependencies":{},"optionalDependencies":{},"_engineSupported":true,"_npmVersion":"1.1.4","_nodeVersion":"v0.6.12","_defaultsLoaded":true,"dist":{"shasum":"7973e824448265656bfb73572468f5dd21e0a512","tarball":"https://registry.npmjs.org/mixpanel/-/mixpanel-0.0.11.tgz"},"maintainers":[{"name":"carlsverre","email":"mail@carlsverre.com"}]},"0.0.12":{"name":"mixpanel","description":"A simple API for mixpanel","keywords":["mixpanel","analytics","api","stats"],"version":"0.0.12","homepage":"https://github.com/carlsverre/mixpanel-node","author":{"name":"Carl Sverre"},"main":"lib/mixpanel-node","directories":{"lib":"lib"},"repository":{"type":"git","url":"git://github.com/carlsverre/mixpanel-node.git"},"engines":{"node":">=0.6.0"},"scripts":{"test":"bin/run_tests"},"devDependencies":{"nodeunit":"0.7","sinon":"1.4"},"_npmUser":{"name":"carlsverre","email":"accounts@carlsverre.com"},"_id":"mixpanel@0.0.12","dependencies":{},"optionalDependencies":{},"_engineSupported":true,"_npmVersion":"1.1.4","_nodeVersion":"v0.6.12","_defaultsLoaded":true,"dist":{"shasum":"687d53ad74b8485c17171f1c3420fb9f39570470","tarball":"https://registry.npmjs.org/mixpanel/-/mixpanel-0.0.12.tgz"},"maintainers":[{"name":"carlsverre","email":"mail@carlsverre.com"}]},"0.0.13":{"name":"mixpanel","description":"A simple API for mixpanel","keywords":["mixpanel","analytics","api","stats"],"version":"0.0.13","homepage":"https://github.com/carlsverre/mixpanel-node","author":{"name":"Carl Sverre"},"main":"lib/mixpanel-node","directories":{"lib":"lib"},"repository":{"type":"git","url":"http://github.com/carlsverre/mixpanel-node.git"},"engines":{"node":">=0.6.0"},"scripts":{"test":"bin/run_tests"},"devDependencies":{"nodeunit":"0.7","sinon":"1.4"},"_id":"mixpanel@0.0.13","dist":{"shasum":"eb4efdf03314a81aba78be304421e8c0fbac713f","tarball":"https://registry.npmjs.org/mixpanel/-/mixpanel-0.0.13.tgz"},"_npmVersion":"1.1.63","_npmUser":{"name":"carlsverre","email":"accounts@carlsverre.com"},"maintainers":[{"name":"carlsverre","email":"mail@carlsverre.com"}],"deprecated":"0.0.13 doesn't have https functionality."},"0.0.14":{"name":"mixpanel","description":"A simple API for mixpanel","keywords":["mixpanel","analytics","api","stats"],"version":"0.0.14","homepage":"https://github.com/carlsverre/mixpanel-node","author":{"name":"Carl Sverre"},"main":"lib/mixpanel-node","directories":{"lib":"lib"},"repository":{"type":"git","url":"http://github.com/carlsverre/mixpanel-node.git"},"engines":{"node":">=0.6.0"},"scripts":{"test":"bin/run_tests"},"devDependencies":{"nodeunit":"0.7","sinon":"1.4"},"_id":"mixpanel@0.0.14","dist":{"shasum":"d16bf7c3b5ac12cda0d0a16f139b6539ade1339f","tarball":"https://registry.npmjs.org/mixpanel/-/mixpanel-0.0.14.tgz"},"_npmVersion":"1.1.63","_npmUser":{"name":"carlsverre","email":"accounts@carlsverre.com"},"maintainers":[{"name":"carlsverre","email":"mail@carlsverre.com"}]},"0.0.15":{"name":"mixpanel","description":"A simple API for mixpanel","keywords":["mixpanel","analytics","api","stats"],"version":"0.0.15","homepage":"https://github.com/carlsverre/mixpanel-node","author":{"name":"Carl Sverre"},"main":"lib/mixpanel-node","directories":{"lib":"lib"},"repository":{"type":"git","url":"http://github.com/carlsverre/mixpanel-node.git"},"engines":{"node":">=0.6.0"},"scripts":{"test":"bin/run_tests"},"devDependencies":{"nodeunit":"0.7","sinon":"1.4"},"_id":"mixpanel@0.0.15","dist":{"shasum":"237f00760a3cefae9660c4c4efacb66325f57a48","tarball":"https://registry.npmjs.org/mixpanel/-/mixpanel-0.0.15.tgz"},"_npmVersion":"1.1.63","_npmUser":{"name":"carlsverre","email":"accounts@carlsverre.com"},"maintainers":[{"name":"carlsverre","email":"mail@carlsverre.com"}]},"0.0.16":{"name":"mixpanel","description":"A simple API for mixpanel","keywords":["mixpanel","analytics","api","stats"],"version":"0.0.16","homepage":"https://github.com/carlsverre/mixpanel-node","author":{"name":"Carl Sverre"},"main":"lib/mixpanel-node","directories":{"lib":"lib"},"repository":{"type":"git","url":"http://github.com/carlsverre/mixpanel-node.git"},"engines":{"node":">=0.6.0"},"scripts":{"test":"bin/run_tests"},"devDependencies":{"nodeunit":"0.7","sinon":"1.4"},"_id":"mixpanel@0.0.16","dist":{"shasum":"7d2bebe1ed21a39f1ffffcc9e9ed5ad0d6f8babb","tarball":"https://registry.npmjs.org/mixpanel/-/mixpanel-0.0.16.tgz"},"_from":".","_npmVersion":"1.2.11","_npmUser":{"name":"carlsverre","email":"accounts@carlsverre.com"},"maintainers":[{"name":"carlsverre","email":"mail@carlsverre.com"}]},"0.0.17":{"name":"mixpanel","description":"A simple API for mixpanel","keywords":["mixpanel","analytics","api","stats"],"version":"0.0.17","homepage":"https://github.com/carlsverre/mixpanel-node","author":{"name":"Carl Sverre"},"main":"lib/mixpanel-node","directories":{"lib":"lib"},"repository":{"type":"git","url":"http://github.com/carlsverre/mixpanel-node.git"},"engines":{"node":">=0.6.0"},"scripts":{"test":"bin/run_tests"},"devDependencies":{"nodeunit":"0.7","sinon":"1.4"},"_id":"mixpanel@0.0.17","dist":{"shasum":"1a3785a06e8f7f71abb4345f060beb17aecb96f3","tarball":"https://registry.npmjs.org/mixpanel/-/mixpanel-0.0.17.tgz"},"_from":".","_npmVersion":"1.2.11","_npmUser":{"name":"carlsverre","email":"accounts@carlsverre.com"},"maintainers":[{"name":"carlsverre","email":"mail@carlsverre.com"}]},"0.0.18":{"name":"mixpanel","description":"A simple API for mixpanel","keywords":["mixpanel","analytics","api","stats"],"version":"0.0.18","homepage":"https://github.com/carlsverre/mixpanel-node","author":{"name":"Carl Sverre"},"main":"lib/mixpanel-node","directories":{"lib":"lib"},"repository":{"type":"git","url":"http://github.com/carlsverre/mixpanel-node.git"},"engines":{"node":">=0.6.0"},"scripts":{"test":"bin/run_tests"},"devDependencies":{"nodeunit":"0.7","sinon":"1.4"},"_id":"mixpanel@0.0.18","dist":{"shasum":"ee0a21fb3adc2703ce432b6a7274161964ca9dcd","tarball":"https://registry.npmjs.org/mixpanel/-/mixpanel-0.0.18.tgz"},"_from":".","_npmVersion":"1.2.11","_npmUser":{"name":"carlsverre","email":"accounts@carlsverre.com"},"maintainers":[{"name":"carlsverre","email":"mail@carlsverre.com"}]},"0.0.19":{"name":"mixpanel","description":"A simple API for mixpanel","keywords":["mixpanel","analytics","api","stats"],"version":"0.0.19","homepage":"https://github.com/carlsverre/mixpanel-node","author":{"name":"Carl Sverre"},"main":"lib/mixpanel-node","directories":{"lib":"lib"},"repository":{"type":"git","url":"http://github.com/carlsverre/mixpanel-node.git"},"engines":{"node":">=0.6.0"},"scripts":{"test":"bin/run_tests"},"devDependencies":{"nodeunit":"0.7","sinon":"1.4"},"bugs":{"url":"https://github.com/carlsverre/mixpanel-node/issues"},"_id":"mixpanel@0.0.19","dist":{"shasum":"c26743e0385992bab6f7293759975022faa83b2b","tarball":"https://registry.npmjs.org/mixpanel/-/mixpanel-0.0.19.tgz"},"_from":".","_npmVersion":"1.4.3","_npmUser":{"name":"carlsverre","email":"accounts@carlsverre.com"},"maintainers":[{"name":"carlsverre","email":"mail@carlsverre.com"}]},"0.0.20":{"name":"mixpanel","description":"A simple API for mixpanel","keywords":["mixpanel","analytics","api","stats"],"version":"0.0.20","homepage":"https://github.com/carlsverre/mixpanel-node","author":{"name":"Carl Sverre"},"main":"lib/mixpanel-node","directories":{"lib":"lib"},"repository":{"type":"git","url":"http://github.com/carlsverre/mixpanel-node.git"},"engines":{"node":">=0.6.0"},"scripts":{"test":"bin/run_tests"},"devDependencies":{"nodeunit":"0.7","sinon":"1.4"},"bugs":{"url":"https://github.com/carlsverre/mixpanel-node/issues"},"_id":"mixpanel@0.0.20","dist":{"shasum":"cfae1145594ee9c45be9834548c7472ff81317dd","tarball":"https://registry.npmjs.org/mixpanel/-/mixpanel-0.0.20.tgz"},"_from":".","_npmVersion":"1.4.3","_npmUser":{"name":"carlsverre","email":"accounts@carlsverre.com"},"maintainers":[{"name":"carlsverre","email":"mail@carlsverre.com"}]},"0.1.0":{"name":"mixpanel","description":"A simple API for mixpanel","keywords":["mixpanel","analytics","api","stats"],"version":"0.1.0","homepage":"https://github.com/mixpanel/mixpanel-node","author":{"name":"Carl Sverre"},"main":"lib/mixpanel-node","directories":{"lib":"lib"},"repository":{"type":"git","url":"http://github.com/mixpanel/mixpanel-node.git"},"engines":{"node":">=0.10.0"},"scripts":{"test":"bin/run_tests"},"devDependencies":{"nodeunit":"^0.9.1","sinon":"^1.14.1"},"bugs":{"url":"https://github.com/mixpanel/mixpanel-node/issues"},"_id":"mixpanel@0.1.0","dist":{"shasum":"ad8b975ec94c4fad10e7722816a75c85e61ffa9d","tarball":"https://registry.npmjs.org/mixpanel/-/mixpanel-0.1.0.tgz"},"_from":".","_npmVersion":"1.4.3","_npmUser":{"name":"mixpanel","email":"dev@mixpanel.com"},"maintainers":[{"name":"carlsverre","email":"mail@carlsverre.com"},{"name":"mixpanel","email":"dev@mixpanel.com"}]},"0.1.1":{"name":"mixpanel","description":"A simple API for mixpanel","keywords":["mixpanel","analytics","api","stats"],"version":"0.1.1","homepage":"https://github.com/mixpanel/mixpanel-node","author":{"name":"Carl Sverre"},"main":"lib/mixpanel-node","directories":{"lib":"lib"},"repository":{"type":"git","url":"http://github.com/mixpanel/mixpanel-node.git"},"engines":{"node":">=0.10.0"},"scripts":{"test":"bin/run_tests"},"devDependencies":{"nodeunit":"^0.9.1","sinon":"^1.14.1"},"gitHead":"f42ec21e6a4d5a3fa0656f9a8b206d1b1788bc4f","bugs":{"url":"https://github.com/mixpanel/mixpanel-node/issues"},"_id":"mixpanel@0.1.1","_shasum":"1d324ae6314a74cf46f5f322419f57f4edfe5349","_from":".","_npmVersion":"2.7.0","_nodeVersion":"1.5.1","_npmUser":{"name":"mixpanel","email":"dev@mixpanel.com"},"maintainers":[{"name":"carlsverre","email":"mail@carlsverre.com"},{"name":"mixpanel","email":"dev@mixpanel.com"}],"dist":{"shasum":"1d324ae6314a74cf46f5f322419f57f4edfe5349","tarball":"https://registry.npmjs.org/mixpanel/-/mixpanel-0.1.1.tgz"}},"0.2.0":{"name":"mixpanel","description":"A simple API for mixpanel","keywords":["mixpanel","analytics","api","stats"],"version":"0.2.0","homepage":"https://github.com/mixpanel/mixpanel-node","author":{"name":"Carl Sverre"},"main":"lib/mixpanel-node","directories":{"lib":"lib"},"repository":{"type":"git","url":"http://github.com/mixpanel/mixpanel-node.git"},"engines":{"node":">=0.10.0"},"scripts":{"test":"bin/run_tests"},"devDependencies":{"nodeunit":"^0.9.1","sinon":"^1.14.1"},"gitHead":"3134a957e44955eab5b9605a91036fc2d869da91","bugs":{"url":"https://github.com/mixpanel/mixpanel-node/issues"},"_id":"mixpanel@0.2.0","_shasum":"63c5406035ebcd5e15dac5edb16f9566fea0c8e7","_from":".","_npmVersion":"2.7.0","_nodeVersion":"1.5.1","_npmUser":{"name":"mixpanel","email":"dev@mixpanel.com"},"maintainers":[{"name":"carlsverre","email":"mail@carlsverre.com"},{"name":"mixpanel","email":"dev@mixpanel.com"}],"dist":{"shasum":"63c5406035ebcd5e15dac5edb16f9566fea0c8e7","tarball":"https://registry.npmjs.org/mixpanel/-/mixpanel-0.2.0.tgz"}},"0.2.1":{"name":"mixpanel","description":"A simple server-side API for mixpanel","keywords":["mixpanel","analytics","api","stats"],"version":"0.2.1","homepage":"https://github.com/mixpanel/mixpanel-node","author":{"name":"Carl Sverre"},"main":"lib/mixpanel-node","directories":{"lib":"lib"},"repository":{"type":"git","url":"http://github.com/mixpanel/mixpanel-node.git"},"engines":{"node":">=0.10.0"},"scripts":{"test":"bin/run_tests"},"devDependencies":{"nodeunit":"^0.9.1","sinon":"^1.14.1"},"gitHead":"61513157b012281e807196af4ea4d25c1af4b045","bugs":{"url":"https://github.com/mixpanel/mixpanel-node/issues"},"_id":"mixpanel@0.2.1","_shasum":"c6db3aaf9ad378e08c11e0bebc1c34f3fde2c5c3","_from":".","_npmVersion":"2.7.0","_nodeVersion":"1.5.1","_npmUser":{"name":"mixpanel","email":"dev@mixpanel.com"},"maintainers":[{"name":"carlsverre","email":"mail@carlsverre.com"},{"name":"mixpanel","email":"dev@mixpanel.com"}],"dist":{"shasum":"c6db3aaf9ad378e08c11e0bebc1c34f3fde2c5c3","tarball":"https://registry.npmjs.org/mixpanel/-/mixpanel-0.2.1.tgz"}},"0.3.0":{"name":"mixpanel","description":"A simple server-side API for mixpanel","keywords":["mixpanel","analytics","api","stats"],"version":"0.3.0","homepage":"https://github.com/mixpanel/mixpanel-node","author":{"name":"Carl Sverre"},"main":"lib/mixpanel-node","directories":{"lib":"lib"},"repository":{"type":"git","url":"http://github.com/mixpanel/mixpanel-node.git"},"engines":{"node":">=0.10.0"},"scripts":{"test":"bin/run_tests"},"devDependencies":{"nodeunit":"^0.9.1","sinon":"^1.14.1"},"gitHead":"f60327dcbcddfaab75e7023246040ddc892e4aab","bugs":{"url":"https://github.com/mixpanel/mixpanel-node/issues"},"_id":"mixpanel@0.3.0","_shasum":"b259e38ba6d3e0a202173cd70ff989950e6db163","_from":".","_npmVersion":"2.7.0","_nodeVersion":"1.5.1","_npmUser":{"name":"mixpanel","email":"dev@mixpanel.com"},"maintainers":[{"name":"carlsverre","email":"mail@carlsverre.com"},{"name":"mixpanel","email":"dev@mixpanel.com"}],"dist":{"shasum":"b259e38ba6d3e0a202173cd70ff989950e6db163","tarball":"https://registry.npmjs.org/mixpanel/-/mixpanel-0.3.0.tgz"}},"0.3.1":{"name":"mixpanel","description":"A simple server-side API for mixpanel","keywords":["mixpanel","analytics","api","stats"],"version":"0.3.1","homepage":"https://github.com/mixpanel/mixpanel-node","author":{"name":"Carl Sverre"},"main":"lib/mixpanel-node","directories":{"lib":"lib"},"repository":{"type":"git","url":"http://github.com/mixpanel/mixpanel-node.git"},"engines":{"node":">=0.10.0"},"scripts":{"test":"bin/run_tests"},"devDependencies":{"nodeunit":"^0.9.1","sinon":"^1.14.1"},"gitHead":"87b34b48ca7961bd6f9a222c9631384bec55ce6e","bugs":{"url":"https://github.com/mixpanel/mixpanel-node/issues"},"_id":"mixpanel@0.3.1","_shasum":"f7dadacf0663b4e8f385d67a1abf8dfa260b4b1a","_from":".","_npmVersion":"2.7.0","_nodeVersion":"1.5.1","_npmUser":{"name":"mixpanel","email":"dev@mixpanel.com"},"maintainers":[{"name":"carlsverre","email":"mail@carlsverre.com"},{"name":"mixpanel","email":"dev@mixpanel.com"}],"dist":{"shasum":"f7dadacf0663b4e8f385d67a1abf8dfa260b4b1a","tarball":"https://registry.npmjs.org/mixpanel/-/mixpanel-0.3.1.tgz"}},"0.3.2":{"name":"mixpanel","description":"A simple server-side API for mixpanel","keywords":["mixpanel","analytics","api","stats"],"version":"0.3.2","homepage":"https://github.com/mixpanel/mixpanel-node","author":{"name":"Carl Sverre"},"main":"lib/mixpanel-node","directories":{"lib":"lib"},"repository":{"type":"git","url":"http://github.com/mixpanel/mixpanel-node.git"},"engines":{"node":">=0.10.0"},"scripts":{"test":"nodeunit"},"devDependencies":{"nodeunit":"^0.9.1","sinon":"^1.14.1"},"gitHead":"cea1f875f6c169cc71e3b7ef2180f3dc38a73623","bugs":{"url":"https://github.com/mixpanel/mixpanel-node/issues"},"_id":"mixpanel@0.3.2","_shasum":"69d610bf742144a557b4a6d1e4db64f49522a2d4","_from":".","_npmVersion":"2.7.0","_nodeVersion":"1.5.1","_npmUser":{"name":"mixpanel","email":"dev@mixpanel.com"},"maintainers":[{"name":"carlsverre","email":"mail@carlsverre.com"},{"name":"mixpanel","email":"dev@mixpanel.com"}],"dist":{"shasum":"69d610bf742144a557b4a6d1e4db64f49522a2d4","tarball":"https://registry.npmjs.org/mixpanel/-/mixpanel-0.3.2.tgz"}},"0.4.0":{"name":"mixpanel","description":"A simple server-side API for mixpanel","keywords":["mixpanel","analytics","api","stats"],"version":"0.4.0","homepage":"https://github.com/mixpanel/mixpanel-node","author":{"name":"Carl Sverre"},"main":"lib/mixpanel-node","directories":{"lib":"lib"},"repository":{"type":"git","url":"git+ssh://git@github.com/mixpanel/mixpanel-node.git"},"engines":{"node":">=0.10.0"},"scripts":{"test":"nodeunit"},"devDependencies":{"nodeunit":"^0.9.1","sinon":"^1.14.1"},"gitHead":"cdee8db6ae09d16591633205dcc730a83f600095","bugs":{"url":"https://github.com/mixpanel/mixpanel-node/issues"},"_id":"mixpanel@0.4.0","_shasum":"e99dcbfec77475e69749765732201cbd10268b28","_from":".","_npmVersion":"2.14.7","_nodeVersion":"4.2.3","_npmUser":{"name":"mixpanel","email":"dev@mixpanel.com"},"maintainers":[{"name":"carlsverre","email":"mail@carlsverre.com"},{"name":"mixpanel","email":"dev@mixpanel.com"}],"dist":{"shasum":"e99dcbfec77475e69749765732201cbd10268b28","tarball":"https://registry.npmjs.org/mixpanel/-/mixpanel-0.4.0.tgz"},"_npmOperationalInternal":{"host":"packages-6-west.internal.npmjs.com","tmp":"tmp/mixpanel-0.4.0.tgz_1455052109176_0.9091543508693576"}},"0.4.1":{"name":"mixpanel","description":"A simple server-side API for mixpanel","keywords":["mixpanel","analytics","api","stats"],"version":"0.4.1","homepage":"https://github.com/mixpanel/mixpanel-node","author":{"name":"Carl Sverre"},"license":"MIT","main":"lib/mixpanel-node","directories":{"lib":"lib"},"repository":{"type":"git","url":"git+ssh://git@github.com/mixpanel/mixpanel-node.git"},"engines":{"node":">=0.10.0"},"scripts":{"test":"nodeunit"},"devDependencies":{"nodeunit":"^0.9.1","sinon":"^1.14.1"},"gitHead":"9fcfc12a83dcddf388e2ac40d508c94581d53764","bugs":{"url":"https://github.com/mixpanel/mixpanel-node/issues"},"_id":"mixpanel@0.4.1","_shasum":"0e92ee336fb89a164f54830f093c9cae8517fb8f","_from":".","_npmVersion":"2.14.7","_nodeVersion":"4.2.3","_npmUser":{"name":"tdumitrescu","email":"webdev@cmme.org"},"dist":{"shasum":"0e92ee336fb89a164f54830f093c9cae8517fb8f","tarball":"https://registry.npmjs.org/mixpanel/-/mixpanel-0.4.1.tgz"},"maintainers":[{"name":"carlsverre","email":"accounts@carlsverre.com"},{"name":"mixpanel","email":"dev@mixpanel.com"},{"name":"tdumitrescu","email":"webdev@cmme.org"}],"_npmOperationalInternal":{"host":"packages-12-west.internal.npmjs.com","tmp":"tmp/mixpanel-0.4.1.tgz_1473446521322_0.6881560054607689"}},"0.5.0":{"name":"mixpanel","description":"A simple server-side API for mixpanel","keywords":["mixpanel","analytics","api","stats"],"version":"0.5.0","homepage":"https://github.com/mixpanel/mixpanel-node","author":{"name":"Carl Sverre"},"license":"MIT","main":"lib/mixpanel-node","directories":{"lib":"lib"},"repository":{"type":"git","url":"git+ssh://git@github.com/mixpanel/mixpanel-node.git"},"engines":{"node":">=0.10.0"},"scripts":{"test":"nodeunit"},"devDependencies":{"nodeunit":"^0.9.1","sinon":"^1.14.1"},"gitHead":"07be037143a35eeabced9e2127d324d02280bcc1","bugs":{"url":"https://github.com/mixpanel/mixpanel-node/issues"},"_id":"mixpanel@0.5.0","_shasum":"b40e8a852490a6bc3d21d2f61641d950f8175380","_from":".","_npmVersion":"2.14.7","_nodeVersion":"4.2.3","_npmUser":{"name":"tdumitrescu","email":"webdev@cmme.org"},"dist":{"shasum":"b40e8a852490a6bc3d21d2f61641d950f8175380","tarball":"https://registry.npmjs.org/mixpanel/-/mixpanel-0.5.0.tgz"},"maintainers":[{"name":"carlsverre","email":"accounts@carlsverre.com"},{"name":"mixpanel","email":"dev@mixpanel.com"},{"name":"tdumitrescu","email":"webdev@cmme.org"}],"_npmOperationalInternal":{"host":"packages-12-west.internal.npmjs.com","tmp":"tmp/mixpanel-0.5.0.tgz_1473980024492_0.6951093939132988"}}},"maintainers":[{"name":"carlsverre","email":"accounts@carlsverre.com"},{"name":"mixpanel","email":"dev@mixpanel.com"},{"name":"tdumitrescu","email":"webdev@cmme.org"}],"time":{"modified":"2016-09-15T22:53:44.732Z","created":"2011-02-07T03:01:50.099Z","0.0.2":"2011-02-07T03:01:50.426Z","0.0.3":"2011-02-11T01:31:20.784Z","0.0.4":"2011-06-08T06:43:57.298Z","0.0.5":"2011-09-27T19:16:46.735Z","0.0.6":"2012-08-31T20:16:24.584Z","0.0.7":"2012-09-06T00:51:17.080Z","0.0.8":"2012-10-24T21:30:01.620Z","0.0.9":"2012-11-16T01:40:10.466Z","0.0.10":"2012-11-26T20:38:17.293Z","0.0.11":"2013-01-12T01:51:45.924Z","0.0.12":"2013-01-24T18:21:22.275Z","0.0.13":"2013-03-26T06:28:33.758Z","0.0.14":"2013-03-28T07:25:45.192Z","0.0.15":"2013-05-25T04:20:51.242Z","0.0.16":"2013-06-30T02:44:01.045Z","0.0.17":"2013-08-12T17:59:54.540Z","0.0.18":"2013-08-23T23:33:16.943Z","0.0.19":"2014-04-04T16:23:35.290Z","0.0.20":"2014-05-12T00:43:14.287Z","0.1.0":"2015-03-20T17:57:45.788Z","0.1.1":"2015-03-27T19:07:32.813Z","0.2.0":"2015-04-15T02:35:09.601Z","0.2.1":"2015-05-12T22:36:20.206Z","0.3.0":"2015-08-06T18:36:47.196Z","0.3.1":"2015-08-12T02:06:34.332Z","0.3.2":"2015-12-11T02:13:02.314Z","0.4.0":"2016-02-09T21:08:30.486Z","0.4.1":"2016-09-09T18:42:01.575Z","0.5.0":"2016-09-15T22:53:44.732Z"},"author":{"name":"Carl Sverre"},"repository":{"type":"git","url":"git+ssh://git@github.com/mixpanel/mixpanel-node.git"},"readme":"Mixpanel-node\n=============\n[![Build Status](https://travis-ci.org/mixpanel/mixpanel-node.svg?branch=master)](https://travis-ci.org/mixpanel/mixpanel-node)\n\nThis library provides many of the features in the official JavaScript mixpanel library.  It is easy to use, and fully async. It is intended to be used on the server (it is not a client module). The in-browser client library is available\nat [https://github.com/mixpanel/mixpanel-js](https://github.com/mixpanel/mixpanel-js).\n\nInstallation\n------------\n\n    npm install mixpanel\n\nQuick Start\n-----------\n\n```javascript\n// grab the Mixpanel factory\nvar Mixpanel = require('mixpanel');\n\n// create an instance of the mixpanel client\nvar mixpanel = Mixpanel.init('6fd9434dba686db2d1ab66b4462a3a67');\n\n// initialize mixpanel client configured to communicate over https\nvar mixpanel = Mixpanel.init('6fd9434dba686db2d1ab66b4462a3a67', {\n    protocol: 'https'\n});\n\n// track an event with optional properties\nmixpanel.track('my event', {\n    distinct_id: 'some unique client id',\n    as: 'many',\n    properties: 'as',\n    you: 'want'\n});\nmixpanel.track('played_game');\n\n// create or update a user in Mixpanel Engage\nmixpanel.people.set('billybob', {\n    $first_name: 'Billy',\n    $last_name: 'Bob',\n    $created: (new Date('jan 1 2013')).toISOString(),\n    plan: 'premium',\n    games_played: 1,\n    points: 0\n});\n\n// create or update a user in Mixpanel Engage without altering $last_seen\n// - pass option $ignore_time: true to prevent the $last_seen property from being updated\nmixpanel.people.set('billybob', {\n    plan: 'premium',\n    games_played: 1\n}, {\n    $ignore_time: true\n});\n\n// set a single property on a user\nmixpanel.people.set('billybob', 'plan', 'free');\n\n// set a single property on a user, don't override\nmixpanel.people.set_once('billybob', 'first_game_play', (new Date('jan 1 2013')).toISOString());\n\n// increment a numeric property\nmixpanel.people.increment('billybob', 'games_played');\n\n// increment a numeric property by a different amount\nmixpanel.people.increment('billybob', 'points', 15);\n\n// increment multiple properties\nmixpanel.people.increment('billybob', {'points': 10, 'games_played': 1});\n\n// append value to a list\nmixpanel.people.append('billybob', 'awards', 'Great Player');\n\n// append multiple values to a list\nmixpanel.people.append('billybob', {'awards': 'Great Player', 'levels_finished': 'Level 4'});\n\n// merge value to a list (ignoring duplicates)\nmixpanel.people.union('billybob', {'browsers': 'ie'});\n\n// merge multiple values to a list (ignoring duplicates)\nmixpanel.people.union('billybob', {'browsers': ['ie', 'chrome']});\n\n\n// record a transaction for revenue analytics\nmixpanel.people.track_charge('billybob', 39.99);\n\n// clear a users transaction history\nmixpanel.people.clear_charges('billybob');\n\n// delete a user\nmixpanel.people.delete_user('billybob');\n\n// delete a user in Mixpanel Engage without altering $last_seen or resolving aliases\n// - pass option $ignore_time: true to prevent the $last_seen property from being updated\n// (useful if you subsequently re-import data for the same distinct ID)\nmixpanel.people.delete_user('billybob', {$ignore_time: true, $ignore_alias: true});\n\n// Create an alias for an existing distinct id\nmixpanel.alias('distinct_id', 'your_alias');\n\n// all functions that send data to mixpanel take an optional\n// callback as the last argument\nmixpanel.track('test', function(err) { if (err) throw err; });\n\n// import an old event\nvar mixpanel_importer = Mixpanel.init('valid mixpanel token', {\n    key: 'valid api key for project'\n});\n\n// needs to be in the system once for it to show up in the interface\nmixpanel_importer.track('old event', { gender: '' });\n\nmixpanel_importer.import('old event', new Date(2012, 4, 20, 12, 34, 56), {\n    distinct_id: 'billybob',\n    gender: 'male'\n});\n\n// import multiple events at once\nmixpanel_importer.import_batch([\n    {\n        event: 'old event',\n        properties: {\n            time: new Date(2012, 4, 20, 12, 34, 56),\n            distinct_id: 'billybob',\n            gender: 'male'\n        }\n    },\n    {\n        event: 'another old event',\n        properties: {\n            time: new Date(2012, 4, 21, 11, 33, 55),\n            distinct_id: 'billybob',\n            color: 'red'\n        }\n    }\n]);\n```\n\nFAQ\n---\n**Where is `mixpanel.identify()`?**\n\n`mixpanel-node` is a server-side library, optimized for stateless shared usage; e.g.,\nin a web application, the same mixpanel instance is used across requests for all users.\nRather than setting a `distinct_id` through `identify()` calls like Mixpanel client-side\nlibraries (where a single Mixpanel instance is tied to a single user), this library\nrequires you to pass the `distinct_id` with every tracking call. See\nhttps://github.com/mixpanel/mixpanel-node/issues/13.\n\n**How do I get or set superproperties?**\n\nSee the previous answer: the library does not maintain user state internally and so has\nno concept of superproperties for individual users. If you wish to preserve properties\nfor users between requests, you will need to load these properties from a source specific\nto your app (e.g., your session store or database) and pass them explicitly with each\ntracking call.\n\n\nTests\n-----\n\n    # in the mixpanel directory\n    npm install\n    npm test\n\nAttribution/Credits\n-------------------\n\nHeavily inspired by the original js library copyright Mixpanel, Inc.\n(http://mixpanel.com/)\n\nCopyright (c) 2014-15 Mixpanel\nOriginal Library Copyright (c) 2012-14 Carl Sverre\n\nContributions from:\n - [Andres Gottlieb](https://github.com/andresgottlieb)\n - [Ken Perkins](https://github.com/kenperkins)\n - [Nathan Rajlich](https://github.com/TooTallNate)\n - [Thomas Watson Steen](https://github.com/watson)\n - [Gabor Ratky](https://github.com/rgabo)\n - [wwlinx](https://github.com/wwlinx)\n - [PierrickP](https://github.com/PierrickP)\n - [lukapril](https://github.com/lukapril)\n - [sandinmyjoints](https://github.com/sandinmyjoints)\n - [Jyrki Laurila](https://github.com/jylauril)\n - [Zeevl](https://github.com/zeevl)\n - [Tobias Baunbæk](https://github.com/freeall)\n - [Eduardo Sorribas](https://github.com/sorribas)\n - [Nick Chang](https://github.com/maeldur)\n - [Michael G](https://github.com/gmichael225)\n - [Tejas Manohar](https://github.com/tejasmanohar)\n - [Eelke Boezeman](https://github.com/godspeedelbow)\n - [Jim Thomas](https://github.com/Left47)\n - [Frank Chiang](https://github.com/chiangf)\n\nLicense\n-------------------\n\nReleased under the MIT license.  See file called LICENSE for more\ndetails.\n","homepage":"https://github.com/mixpanel/mixpanel-node","keywords":["mixpanel","analytics","api","stats"],"readmeFilename":"readme.md","bugs":{"url":"https://github.com/mixpanel/mixpanel-node/issues"},"users":{"vboctor":true,"brentchow":true,"chmod0":true,"hengkiardo":true,"arunrajmony":true},"license":"MIT","_attachments":{},"_etag":"W/\"57db2678-89b4\"","_lastModified":"Thu, 15 Sep 2016 22:53:44 GMT","_cached":true}